[
  {
    "start": 18.609,
    "end": 18.809,
    "word": "ମପଟ",
    "probability": 0.7276656928029334
  },
  {
    "start": 18.809,
    "end": 19.05,
    "word": "ଏବ",
    "probability": 0.7630180635880834
  },
  {
    "start": 19.05,
    "end": 20.07,
    "word": "ମଟନସ",
    "probability": 0.8662418923895251
  },
  {
    "start": 20.07,
    "end": 20.45,
    "word": "ବଗଚ",
    "probability": 0.8062265210294561
  },
  {
    "start": 20.45,
    "end": 21.491,
    "word": "ରସତର",
    "probability": 0.8895090373998543
  },
  {
    "start": 21.491,
    "end": 22.111,
    "word": "ଟଳମଳ",
    "probability": 0.8104748658372031
  },
  {
    "start": 22.111,
    "end": 22.371,
    "word": "ହଇ",
    "probability": 0.7442489862354917
  },
  {
    "start": 22.371,
    "end": 22.571,
    "word": "ଗଲ",
    "probability": 0.7861159386349125
  },
  {
    "start": 22.571,
    "end": 22.831,
    "word": "ଶଘର",
    "probability": 0.7242301239313971
  },
  {
    "start": 22.831,
    "end": 23.532,
    "word": "ସମନ",
    "probability": 0.8835297100361907
  },
  {
    "start": 23.532,
    "end": 23.672,
    "word": "ନଜ",
    "probability": 0.7068800435647867
  },
  {
    "start": 23.672,
    "end": 24.032,
    "word": "ପଷକର",
    "probability": 0.7493639842228682
  },
  {
    "start": 24.032,
    "end": 24.152,
    "word": "ଠକର",
    "probability": 0.48960069467171824
  },
  {
    "start": 24.152,
    "end": 24.292,
    "word": "ଖଇ",
    "probability": 0.6722660250352674
  },
  {
    "start": 24.292,
    "end": 24.372,
    "word": "ମହ",
    "probability": 0.47945161330189834
  },
  {
    "start": 24.372,
    "end": 24.552,
    "word": "ମଡ",
    "probability": 0.7590880483724908
  },
  {
    "start": 24.552,
    "end": 24.672,
    "word": "ପଡଲ",
    "probability": 0.40903280138234993
  },
  {
    "start": 24.672,
    "end": 26.033,
    "word": "ଯତବଳ",
    "probability": 0.9334425318577831
  },
  {
    "start": 26.033,
    "end": 26.373,
    "word": "ସମନ",
    "probability": 0.7934362973776681
  },
  {
    "start": 26.373,
    "end": 26.913,
    "word": "ଉଠଲ",
    "probability": 0.7355909576086852
  },
  {
    "start": 26.913,
    "end": 27.134,
    "word": "ସମନ",
    "probability": 0.6480006716338416
  },
  {
    "start": 27.134,
    "end": 27.334,
    "word": "ଘସ",
    "probability": 0.7449125877660805
  },
  {
    "start": 27.334,
    "end": 27.594,
    "word": "ଦଗର",
    "probability": 0.6352251600752582
  },
  {
    "start": 27.594,
    "end": 28.554,
    "word": "ଆଚଛଦତ",
    "probability": 0.8215282825161011
  },
  {
    "start": 28.554,
    "end": 29.015,
    "word": "ହଇଥଲ",
    "probability": 0.7611859221884438
  },
  {
    "start": 29.015,
    "end": 29.195,
    "word": "ମପଟ",
    "probability": 0.6079817155636724
  },
  {
    "start": 29.195,
    "end": 29.595,
    "word": "ପରମରଶ",
    "probability": 0.6909987382041038
  },
  {
    "start": 29.595,
    "end": 29.835,
    "word": "ଦଲ",
    "probability": 0.6944551705382948
  },
  {
    "start": 29.835,
    "end": 30.015,
    "word": "ଆସ",
    "probability": 0.7275605472352418
  },
  {
    "start": 30.015,
    "end": 30.875,
    "word": "ପଥର",
    "probability": 0.9035840489034718
  },
  {
    "start": 30.875,
    "end": 31.156,
    "word": "ଉପର",
    "probability": 0.6862533729407193
  },
  {
    "start": 31.156,
    "end": 31.256,
    "word": "ଚଢ",
    "probability": 0.5933582928086351
  },
  {
    "start": 31.256,
    "end": 31.756,
    "word": "ବଗଚ",
    "probability": 0.7107346946646734
  },
  {
    "start": 31.756,
    "end": 32.076,
    "word": "କନଥ",
    "probability": 0.7332689720389008
  },
  {
    "start": 32.076,
    "end": 32.316,
    "word": "ଉପର",
    "probability": 0.694633841228312
  },
  {
    "start": 32.316,
    "end": 32.516,
    "word": "ବସବ",
    "probability": 0.7340071203225107
  }
]