[
  {
    "start": 0.06,
    "end": 0.381,
    "word": "นายเดรก",
    "probability": 0.7619591065035267
  },
  {
    "start": 0.381,
    "end": 1.003,
    "word": "พดเดลดก",
    "probability": 0.8138441089535745
  },
  {
    "start": 1.003,
    "end": 2.749,
    "word": "เดนเตาะแตะเขามาอยางชาๆ",
    "probability": 0.8448439166475391
  },
  {
    "start": 2.749,
    "end": 4.113,
    "word": "ในทาตะแคงขาง",
    "probability": 0.7986130957904907
  },
  {
    "start": 4.113,
    "end": 5.538,
    "word": "และเกบสงของตางๆ",
    "probability": 0.8522181911758442
  },
  {
    "start": 5.538,
    "end": 5.698,
    "word": "ขนมา",
    "probability": 0.6242193810735293
  }
]