[
  {
    "start": 0.541,
    "end": 1.321,
    "word": "當牠們正忙亂時",
    "probability": 0.7656933576445785
  },
  {
    "start": 1.321,
    "end": 2.763,
    "word": "聽到了",
    "probability": 0.8954880431974566
  },
  {
    "start": 2.763,
    "end": 3.223,
    "word": "啪嗒",
    "probability": 0.914563344259669
  },
  {
    "start": 3.223,
    "end": 4.124,
    "word": "啪嗒",
    "probability": 0.9100003659311178
  },
  {
    "start": 4.124,
    "end": 5.386,
    "word": "划水",
    "probability": 0.9161184842550435
  },
  {
    "start": 5.386,
    "end": 6.046,
    "word": "啪嗒",
    "probability": 0.9167311908988947
  },
  {
    "start": 6.046,
    "end": 7.207,
    "word": "的聲音",
    "probability": 0.8617799939385794
  },
  {
    "start": 7.207,
    "end": 9.39,
    "word": "三隻帕德",
    "probability": 0.9184454070012592
  },
  {
    "start": 9.39,
    "end": 10.351,
    "word": "爾鴨排成",
    "probability": 0.8271103006296733
  },
  {
    "start": 10.351,
    "end": 10.751,
    "word": "一列",
    "probability": 0.9221053505691957
  },
  {
    "start": 10.751,
    "end": 12.052,
    "word": "踏著有節",
    "probability": 0.8830667129650885
  },
  {
    "start": 12.052,
    "end": 12.813,
    "word": "奏的步伐",
    "probability": 0.857218173834927
  },
  {
    "start": 12.813,
    "end": 14.475,
    "word": "沿著馬路",
    "probability": 0.7814294762240294
  },
  {
    "start": 14.475,
    "end": 14.895,
    "word": "走來",
    "probability": 0.8567339630111664
  },
  {
    "start": 14.895,
    "end": 15.696,
    "word": "啪嗒",
    "probability": 0.9258953755900444
  },
  {
    "start": 15.696,
    "end": 16.637,
    "word": "啪嗒",
    "probability": 0.9329960700937855
  },
  {
    "start": 16.637,
    "end": 17.979,
    "word": "划水",
    "probability": 0.9494805371261362
  },
  {
    "start": 17.979,
    "end": 18.659,
    "word": "啪嗒",
    "probability": 0.940577701676782
  },
  {
    "start": 18.659,
    "end": 19.7,
    "word": "啪嗒",
    "probability": 0.9346190319714716
  },
  {
    "start": 19.7,
    "end": 20.681,
    "word": "啪嗒",
    "probability": 0.9322632994402046
  },
  {
    "start": 20.681,
    "end": 21.682,
    "word": "搖擺",
    "probability": 0.9230768809923313
  },
  {
    "start": 21.682,
    "end": 21.923,
    "word": "啪嗒",
    "probability": 0.8856342215228531
  }
]