[
  {
    "start": 0.1,
    "end": 0.4,
    "word": "有一天",
    "probability": 0.9751476978494441
  },
  {
    "start": 0.4,
    "end": 1.501,
    "word": "牠們的媽媽",
    "probability": 0.9088526051874535
  },
  {
    "start": 1.501,
    "end": 2.342,
    "word": "Tabitha",
    "probability": 0.8048140387381858
  },
  {
    "start": 2.342,
    "end": 4.444,
    "word": "Twitchit",
    "probability": 0.9141503905201359
  },
  {
    "start": 4.444,
    "end": 4.945,
    "word": "太太",
    "probability": 0.8909431421232425
  },
  {
    "start": 4.945,
    "end": 6.787,
    "word": "正準備招",
    "probability": 0.948107396163785
  },
  {
    "start": 6.787,
    "end": 7.507,
    "word": "待朋友們",
    "probability": 0.9261113681305514
  },
  {
    "start": 7.507,
    "end": 8.308,
    "word": "來喝茶",
    "probability": 0.8965297315840928
  },
  {
    "start": 8.308,
    "end": 10.43,
    "word": "在客人到達之前",
    "probability": 0.9653991431957456
  },
  {
    "start": 10.43,
    "end": 11.731,
    "word": "她把小貓",
    "probability": 0.970367266625271
  },
  {
    "start": 11.731,
    "end": 12.632,
    "word": "們帶進屋",
    "probability": 0.8893578586267875
  },
  {
    "start": 12.632,
    "end": 13.793,
    "word": "裡洗澡並",
    "probability": 0.9431992045146453
  },
  {
    "start": 13.793,
    "end": 14.834,
    "word": "幫牠們穿",
    "probability": 0.9040422737792594
  },
  {
    "start": 14.834,
    "end": 15.095,
    "word": "衣服",
    "probability": 0.846799097921897
  }
]