[
  {
    "start": 0.52,
    "end": 0.72,
    "word": "米騰絲笑",
    "probability": 0.6744438955475283
  },
  {
    "start": 0.72,
    "end": 1.581,
    "word": "得太犀利",
    "probability": 0.7839548022013915
  },
  {
    "start": 1.581,
    "end": 2.842,
    "word": "喺牆上面",
    "probability": 0.8747727740275936
  },
  {
    "start": 2.842,
    "end": 3.823,
    "word": "跌咗落嚟",
    "probability": 0.8427459294849706
  },
  {
    "start": 3.823,
    "end": 4.843,
    "word": "Moppet",
    "probability": 0.8082459301609041
  },
  {
    "start": 4.843,
    "end": 5.204,
    "word": "同",
    "probability": 0.865587357181579
  },
  {
    "start": 5.204,
    "end": 6.064,
    "word": "Tom",
    "probability": 0.8841656424072042
  },
  {
    "start": 6.064,
    "end": 6.845,
    "word": "跟住佢爬咗落去",
    "probability": 0.7497205953396051
  },
  {
    "start": 6.845,
    "end": 8.786,
    "word": "喺落去嘅途中",
    "probability": 0.8482282713459514
  },
  {
    "start": 8.786,
    "end": 10.047,
    "word": "連身裙同",
    "probability": 0.8878515982277884
  },
  {
    "start": 10.047,
    "end": 10.627,
    "word": "Tom",
    "probability": 0.8601684104597672
  },
  {
    "start": 10.627,
    "end": 11.548,
    "word": "剩低嘅衫",
    "probability": 0.8519945574570208
  },
  {
    "start": 11.548,
    "end": 12.689,
    "word": "全部都除",
    "probability": 0.8975158535715652
  },
  {
    "start": 12.689,
    "end": 13.429,
    "word": "晒落嚟",
    "probability": 0.8749401285792671
  },
  {
    "start": 13.429,
    "end": 14.11,
    "word": "Drake",
    "probability": 0.8171673322190385
  },
  {
    "start": 14.11,
    "end": 14.55,
    "word": "Pudd",
    "probability": 0.7674473027899292
  },
  {
    "start": 14.55,
    "end": 14.71,
    "word": "leD",
    "probability": 0.5429428679099382
  },
  {
    "start": 14.71,
    "end": 15.551,
    "word": "uck",
    "probability": 0.9057064128613357
  },
  {
    "start": 15.551,
    "end": 16.051,
    "word": "先生",
    "probability": 0.8798969486205378
  },
  {
    "start": 16.051,
    "end": 17.092,
    "word": "Moppet",
    "probability": 0.8531854575008365
  },
  {
    "start": 17.092,
    "end": 17.612,
    "word": "嗌道",
    "probability": 0.8820561303255917
  },
  {
    "start": 17.612,
    "end": 18.773,
    "word": "快啲嚟幫",
    "probability": 0.887646788369327
  },
  {
    "start": 18.773,
    "end": 19.694,
    "word": "我哋幫佢",
    "probability": 0.8854290300736958
  },
  {
    "start": 19.694,
    "end": 20.434,
    "word": "著返衫",
    "probability": 0.8804947532018382
  },
  {
    "start": 20.434,
    "end": 21.795,
    "word": "快啲嚟幫",
    "probability": 0.8989250894836757
  },
  {
    "start": 21.795,
    "end": 22.155,
    "word": "Tom",
    "probability": 0.8022645572210915
  },
  {
    "start": 22.155,
    "end": 22.976,
    "word": "扣返鈕",
    "probability": 0.922107991100008
  }
]