[
  {
    "start": 3.1,
    "end": 3.794,
    "word": "તણ",
    "probability": 0.9090795023359486
  },
  {
    "start": 3.794,
    "end": 4.299,
    "word": "તઓન",
    "probability": 0.6249648640921553
  },
  {
    "start": 4.299,
    "end": 5.755,
    "word": "ઉપર",
    "probability": 0.9563814757888313
  },
  {
    "start": 5.755,
    "end": 6.007,
    "word": "મકલય",
    "probability": 0.24965888208094278
  },
  {
    "start": 6.007,
    "end": 6.196,
    "word": "અન",
    "probability": 0.33333348242150285
  },
  {
    "start": 6.196,
    "end": 6.323,
    "word": "મન",
    "probability": 0.49995684422634334
  },
  {
    "start": 6.323,
    "end": 7.589,
    "word": "પસતવ",
    "probability": 0.7521447717986314
  },
  {
    "start": 7.589,
    "end": 7.715,
    "word": "થય",
    "probability": 0.01
  },
  {
    "start": 7.715,
    "end": 7.841,
    "word": "છ",
    "probability": 0.99
  },
  {
    "start": 7.841,
    "end": 7.904,
    "word": "ક",
    "probability": 0.01
  },
  {
    "start": 7.904,
    "end": 8.412,
    "word": "તણ",
    "probability": 0.7495621439444052
  },
  {
    "start": 8.412,
    "end": 8.539,
    "word": "તન",
    "probability": 0.01
  },
  {
    "start": 8.539,
    "end": 10.246,
    "word": "મતરન",
    "probability": 0.851850857141187
  },
  {
    "start": 10.246,
    "end": 10.562,
    "word": "કહય",
    "probability": 0.5992554439195343
  },
  {
    "start": 10.562,
    "end": 10.688,
    "word": "હત",
    "probability": 0.01
  },
  {
    "start": 10.688,
    "end": 11.004,
    "word": "ક",
    "probability": 0.7169579766978347
  },
  {
    "start": 11.004,
    "end": 11.509,
    "word": "તઓ",
    "probability": 0.6266940814950971
  },
  {
    "start": 11.509,
    "end": 12.017,
    "word": "શરદથ",
    "probability": 0.558058654324312
  },
  {
    "start": 12.017,
    "end": 13.027,
    "word": "પથરવશ",
    "probability": 0.7789437342244176
  },
  {
    "start": 13.027,
    "end": 13.217,
    "word": "હત",
    "probability": 0.24999931414816404
  },
  {
    "start": 13.217,
    "end": 13.788,
    "word": "જયર",
    "probability": 0.7758383068436681
  },
  {
    "start": 13.788,
    "end": 13.914,
    "word": "તઓ",
    "probability": 0.01
  },
  {
    "start": 13.914,
    "end": 14.167,
    "word": "નહત",
    "probability": 0.5000407201954847
  }
]